pyempatica/__init__.py
pyempatica/empaticae4.py
pyEmpatica-0.6.0.dist-info/LICENSE
pyEmpatica-0.6.0.dist-info/METADATA
pyEmpatica-0.6.0.dist-info/WHEEL
pyEmpatica-0.6.0.dist-info/top_level.txt
pyEmpatica-0.6.0.dist-info/RECORD
