Metadata-Version: 2.1
Name: pyEmpatica
Version: 0.6.0
Summary: Communicate with your Empatica E4 in your Python scripts.
Home-page: https://github.com/Munroe-Meyer-Institute-VR-Laboratory/pyEmpatica
Author: Walker Arce
Author-email: walker.arce@unmc.edu
Project-URL: Bug Tracker, https://github.com/Munroe-Meyer-Institute-VR-Laboratory/pyEmpatica/issues
Classifier: Programming Language :: Python :: 3
Classifier: License :: OSI Approved :: MIT License
Classifier: Operating System :: OS Independent
Requires-Python: >=3.6
License-File: LICENSE
